dretools-0.0.1.20.data/scripts/dretools
dretoolslib/__init__.py
dretoolslib/diff.py
dretoolslib/io.py
dretoolslib/merge.py
dretoolslib/parsers.py
dretoolslib/shared.py
dretoolslib/stats.py
dretoolslib/units.py
dretools-0.0.1.20.dist-info/LICENSES.md
dretools-0.0.1.20.dist-info/METADATA
dretools-0.0.1.20.dist-info/WHEEL
dretools-0.0.1.20.dist-info/top_level.txt
dretools-0.0.1.20.dist-info/RECORD
